Metadata-Version: 2.1
Name: basic_logtools
Version: 0.1.9
Summary: Some useful tools for log use inside classes
Home-page: https://logtools.readthedocs.io/en/latest/
Author: David Pineda Osorio
Author-email: dpineda@uchile.cl
License: GPLv3
Keywords: logger
Platform: UNKNOWN
